invesyservertools
tests
