Metadata-Version: 2.1
Name: invesyservertools
Version: 0.0.8
Summary: Tools for Python scripts or terminal
Home-page: https://gitlab.com/Rastaf/invesyservertools
Author: Georg Pfolz
Author-email: georg.pfolz@invesy.at
License: MIT License
Project-URL: Bug Tracker, https://gitlab.com/Rastaf/invesyservertools/-/issues
Platform: UNKNOWN
Classifier: Programming Language :: Python :: 3
Classifier: Programming Language :: Python :: 3.7
Classifier: Programming Language :: Python :: 3.8
Classifier: License :: OSI Approved :: MIT License
Classifier: Operating System :: OS Independent
Requires-Python: >=3.7
License-File: LICENSE.txt
